multichat/llm.py
multichat/main.py
multichat-0.3.8.dist-info/licenses/LICENSE
multichat-0.3.8.dist-info/METADATA
multichat-0.3.8.dist-info/WHEEL
multichat-0.3.8.dist-info/entry_points.txt
multichat-0.3.8.dist-info/top_level.txt
multichat-0.3.8.dist-info/RECORD
