Metadata-Version: 2.4
Name: multichat
Version: 0.3.8
Summary: CLI to send the same message to multiple LLMs and return their responses.
Author: Sergey Karayev
License-Expression: Apache-2.0
Project-URL: Homepage, https://github.com/sergeyk/multichat
Project-URL: Issues, https://github.com/sergeyk/multichat/issues
Project-URL: CI, https://github.com/sergeyk/multichat/actions
Project-URL: Changelog, https://github.com/sergeyk/multichat/releases
Requires-Python: >=3.11
License-File: LICENSE
Requires-Dist: any-llm-sdk[anthropic,gemini,openai,xai]>=1.5.0
Requires-Dist: click
Dynamic: license-file
